LICENSE.md
README.md
setup.cfg
setup.py
versioneer.py
mkdocs_snakemake_rule_plugin/__init__.py
mkdocs_snakemake_rule_plugin/_version.py
mkdocs_snakemake_rule_plugin/markdown.py
mkdocs_snakemake_rule_plugin/plugin.py
mkdocs_snakemake_rule_plugin.egg-info/PKG-INFO
mkdocs_snakemake_rule_plugin.egg-info/SOURCES.txt
mkdocs_snakemake_rule_plugin.egg-info/dependency_links.txt
mkdocs_snakemake_rule_plugin.egg-info/entry_points.txt
mkdocs_snakemake_rule_plugin.egg-info/requires.txt
mkdocs_snakemake_rule_plugin.egg-info/top_level.txt