Metadata-Version: 2.1
Name: mkdocs-snakemake-rule-plugin
Version: 0.3.3
Summary: MkDocs Plugin used to extrace rule information, to generate code and tables.
Home-page: https://github.com/smeds/mkdocs-snakemake-rule-plugin
Author: Patrik Smeds
Author-email: patrik.smeds@gmail.com
License: MIT license
Keywords: mkdocs,plugin,yaml,schema
Classifier: Development Status :: 4 - Beta
Classifier: License :: OSI Approved :: MIT License
Classifier: Programming Language :: Python :: 3
Classifier: Programming Language :: Python :: 3.8
Classifier: Programming Language :: Python :: 3.9
Classifier: Programming Language :: Python :: 3.10
Requires-Python: >=3.8, <4
License-File: LICENSE.md
